fate/__init__.py
fate/_info.py
fate/arch/__init__.py
fate/arch/computing/__init__.py
fate/arch/computing/_builder.py
fate/arch/computing/api/__init__.py
fate/arch/computing/api/_table.py
fate/arch/computing/api/_type.py
fate/arch/computing/api/_uuid.py
fate/arch/computing/backends/__init__.py
fate/arch/computing/backends/eggroll/__init__.py
fate/arch/computing/backends/eggroll/_csession.py
fate/arch/computing/backends/eggroll/_table.py
fate/arch/computing/backends/eggroll/_type.py
fate/arch/computing/backends/spark/__init__.py
fate/arch/computing/backends/spark/_csession.py
fate/arch/computing/backends/spark/_materialize.py
fate/arch/computing/backends/spark/_table.py
fate/arch/computing/backends/standalone/__init__.py
fate/arch/computing/backends/standalone/_csession.py
fate/arch/computing/backends/standalone/_standalone.py
fate/arch/computing/backends/standalone/_table.py
fate/arch/computing/backends/standalone/_type.py
fate/arch/computing/partitioners/__init__.py
fate/arch/computing/partitioners/_integer_partitioner.py
fate/arch/computing/partitioners/_java_string_like_partitioner.py
fate/arch/computing/partitioners/_mmh3_partitioner.py
fate/arch/computing/serdes/__init__.py
fate/arch/computing/serdes/_integer_serdes.py
fate/arch/computing/serdes/_restricted_serdes.py
fate/arch/computing/serdes/_safe_serdes.py
fate/arch/computing/serdes/_serdes_base.py
fate/arch/computing/serdes/_unrestricted_serdes.py
fate/arch/config/__init__.py
fate/arch/config/_config.py
fate/arch/config/default.yaml
fate/arch/context/__init__.py
fate/arch/context/_cipher.py
fate/arch/context/_context.py
fate/arch/context/_context_helper.py
fate/arch/context/_metrics.py
fate/arch/context/_mpc.py
fate/arch/context/_namespace.py
fate/arch/context/_parties.py
fate/arch/dataframe/__init__.py
fate/arch/dataframe/_dataframe.py
fate/arch/dataframe/_frame_reader.py
fate/arch/dataframe/conf/__init__.py
fate/arch/dataframe/conf/default_config.py
fate/arch/dataframe/entity/__init__.py
pyfate-2.2.0.dist-info/METADATA
pyfate-2.2.0.dist-info/WHEEL
pyfate-2.2.0.dist-info/top_level.txt
pyfate-2.2.0.dist-info/RECORD
