Metadata-Version: 2.1
Name: pyfate
Version: 2.2.0
Home-page: https://fate.fedai.org/
Author: FederatedAI
Author-email: contact@FedAI.org
License: Apache-2.0 License
Keywords: federated learning
Requires-Python: >=3.8
Requires-Dist: lmdb ==1.4.1
Requires-Dist: torch
Requires-Dist: fate-utils
Requires-Dist: pydantic ==1.10.12
Requires-Dist: cloudpickle ==2.1.0
Requires-Dist: click
Requires-Dist: ruamel.yaml ==0.16
Requires-Dist: scikit-learn ==1.4.1.post1
Requires-Dist: numpy <2.0.0
Requires-Dist: pandas
Requires-Dist: transformers ==4.37.2
Requires-Dist: accelerate ==0.27.2
Requires-Dist: beautifultable
Requires-Dist: requests <2.26.0
Requires-Dist: grpcio ==1.62.1
Requires-Dist: protobuf ==4.24.4
Requires-Dist: rich ==13.7.1
Requires-Dist: omegaconf
Requires-Dist: opentelemetry-api
Requires-Dist: opentelemetry-sdk
Requires-Dist: mmh3 ==3.0.0
Requires-Dist: safetensors ==0.4.1
Provides-Extra: all
Requires-Dist: pyfate[eggroll,pulsar,rabbitmq,spark] ; extra == 'all'
Provides-Extra: eggroll
Requires-Dist: grpcio-tools ==1.62.1 ; extra == 'eggroll'
Requires-Dist: psutil >=5.7.0 ; extra == 'eggroll'
Provides-Extra: pulsar
Requires-Dist: pulsar-client ==3.4.0 ; extra == 'pulsar'
Provides-Extra: rabbitmq
Requires-Dist: pika ; extra == 'rabbitmq'
Provides-Extra: spark
Requires-Dist: pyspark ; extra == 'spark'
